haspirater/__init__.py
haspirater/buildtrie.py
haspirater/buildtrie_list.py
haspirater/compresstrie.py
haspirater/haspirater.json
haspirater/haspirater.py
haspirater/leavestrie.py
haspirater/majoritytrie.py
haspirater/trie2dot.py
haspirater/uptrie.py
haspirater-0.2.dist-info/LICENSE
haspirater-0.2.dist-info/METADATA
haspirater-0.2.dist-info/WHEEL
haspirater-0.2.dist-info/top_level.txt
haspirater-0.2.dist-info/RECORD
