Metadata-Version: 2.1
Name: haspirater
Version: 0.2
Summary: detect aspirated 'h' in French words
Home-page: https://gitlab.com/a3nm/haspirater
Author: Antoine Amarilli
Author-email: a3nm@a3nm.net
License: UNKNOWN
Platform: UNKNOWN
Classifier: Programming Language :: Python :: 3
